memflow-0.2.0.dist-info/METADATA
memflow-0.2.0.dist-info/WHEEL
memflow-0.2.0.dist-info/license_files/LICENSE
memflow/memflow.pyi
memflow/__init__.py
memflow/py.typed
memflow/dummy.pyi
memflow/memflow.abi3.so
memflow-0.2.0.dist-info/RECORD
