Metadata-Version: 2.1
Name: memflow
Version: 0.2.0
Classifier: Programming Language :: Rust
Classifier: License :: OSI Approved :: MIT License
Classifier: Operating System :: OS Independent
Classifier: Topic :: System :: Operating System
Classifier: Typing :: Typed
Requires-Dist: pytest ==7.1 ; extra == 'dev'
Requires-Dist: black ==22.10 ; extra == 'dev'
Provides-Extra: dev
License-File: LICENSE
Summary: Physical memory introspection framework
Keywords: memflow,python
Author: Dan Killinger <git@dank.anonaddy.com>
Author-email: Dan Killinger <git@dank.anonaddy.com>
License: MIT
Requires-Python: >=3.7
Project-URL: Homepage, https://github.com/memflow/memflow-py
Project-URL: Bug Tracker, https://github.com/memflow/memflow-py/issues
